setup.py
tvrage.py
tvrage.egg-info/PKG-INFO
tvrage.egg-info/SOURCES.txt
tvrage.egg-info/dependency_links.txt
tvrage.egg-info/requires.txt
tvrage.egg-info/top_level.txt