Metadata-Version: 1.0
Name: tvrage
Version: 0.1.1
Summary: Python interface to the TVRage television information database.
Home-page: UNKNOWN
Author: Jeremy Cantrell
Author-email: jmcantrell@gmail.com
License: UNKNOWN
Platform: UNKNOWN
Classifier: Development Status :: 4 - Beta
Classifier: License :: OSI Approved :: BSD License
Classifier: Natural Language :: English
Classifier: Operating System :: OS Independent
Classifier: Programming Language :: Python
